mecmitool/__init__.py
mecmitool/decorator.py
mecmitool/errors.py
mecmitool/path_checker.py
mecmitool/playsound.py
mecmitool/playsound.pyi
mecmitool/rgb.py
mecmitool/timer.py
mecmitool/auto_upload/__init__.py
mecmitool/auto_upload/_twine_main.py
mecmitool/auto_upload/auto_upload.py
mecmitool-0.1.2.dist-info/LICENSE
mecmitool-0.1.2.dist-info/METADATA
mecmitool-0.1.2.dist-info/WHEEL
mecmitool-0.1.2.dist-info/top_level.txt
mecmitool-0.1.2.dist-info/RECORD
